[{"Ticker": "PBT", "Rating": 7296184874241.023, "Resistance": [111, 14.265825050483992, 7296178741064.986, "r"], "Support": [104, 11.372755615482594, 6133176.037532479, "s"], "Average Daily Volatility": 0, "Trend": 0, "Potential Profit": 0, "Average Low to Day Open": 0, "Average High to Day Open": 0, "Open Close Average": 0, "Price": 12.94, "Shares": 6035, "Total Spent": 78101}, {"Ticker": "M", "Rating": 2031556988090.222, "Resistance": [110, 27.299999237060547, 2029137874717.1614, "r"], "Support": [102, 22.3700008392334, 2419113373.060616, "s"], "Average Daily Volatility": 0, "Trend": 0, "Potential Profit": 0, "Average Low to Day Open": 0, "Average High to Day Open": 0, "Open Close Average": 0, "Price": 22.38, "Shares": 971, "Total Spent": 21746}, {"Ticker": "PSTI", "Rating": 8766766132.978146, "Resistance": [100, 2.190000057220459, 8766044266.17397, "r"], "Support": [50, 1.3899999856948853, 721866.8041770404, "s"], "Average Daily Volatility": 0, "Trend": 0, "Potential Profit": 0, "Average Low to Day Open": 0, "Average High to Day Open": 0, "Open Close Average": 0, "Price": 1.43, "Shares": 65, "Total Spent": 93}, {"Ticker": "NUVA", "Rating": 2882922139.5365334, "Resistance": [99, 57.93000030517578, 37846110.468709104, "r"], "Support": [84, 48.0099983215332, 2845076029.0678244, "s"], "Average Daily Volatility": 0, "Trend": 0, "Potential Profit": 0, "Average Low to Day Open": 0, "Average High to Day Open": 0, "Open Close Average": 0, "Price": 49.51, "Shares": 0, "Total Spent": 30}, {"Ticker": "MPLN", "Rating": 2522001657.7768564, "Resistance": [118, 4.75, 2479363254.516823, "r"], "Support": [75, 3.484999895095825, 42638403.26003373, "s"], "Average Daily Volatility": 0, "Trend": 0, "Potential Profit": 0, "Average Low to Day Open": 0, "Average High to Day Open": 0, "Open Close Average": 0, "Price": 4.12, "Shares": 6, "Total Spent": 26}, {"Ticker": "FURY", "Rating": 1743426899.2351737, "Resistance": [92, 0.7279999852180481, 17530913.516492654, "r"], "Support": [102, 0.5899999737739563, 1725895985.718681, "s"], "Average Daily Volatility": 0, "Trend": 0, "Potential Profit": 0, "Average Low to Day Open": 0, "Average High to Day Open": 0, "Open Close Average": 0, "Price": 0.0, "Shares": 0, "Total Spent": 0}, {"Ticker": "BCDA", "Rating": 150993182.9418936, "Resistance": [96, 2.200000047683716, 145413701.16019115, "r"], "Support": [108, 1.2799999713897705, 5579481.781702452, "s"], "Average Daily Volatility": 0, "Trend": 0, "Potential Profit": 0, "Average Low to Day Open": 0, "Average High to Day Open": 0, "Open Close Average": 0, "Price": 0.0, "Shares": 0, "Total Spent": 0}, {"Ticker": "DH", "Rating": 133371260.83644366, "Resistance": [119, 25.84000015258789, 130739651.10087262, "r"], "Support": [72, 18.270000457763672, 2631609.7355710487, "s"], "Average Daily Volatility": 0, "Trend": 0, "Potential Profit": 0, "Average Low to Day Open": 0, "Average High to Day Open": 0, "Open Close Average": 0, "Price": 0.0, "Shares": 0, "Total Spent": 0}, {"Ticker": "CAPR", "Rating": 107664940.91842799, "Resistance": [113, 3.380000114440918, 106897400.2809269, "r"], "Support": [116, 2.990000009536743, 767540.6375010926, "s"], "Average Daily Volatility": 0, "Trend": 0, "Potential Profit": 0, "Average Low to Day Open": 0, "Average High to Day Open": 0, "Open Close Average": 0, "Price": 0.0, "Shares": 0, "Total Spent": 0}, {"Ticker": "IIVI", "Rating": 98365189.35102238, "Resistance": [95, 75.05000305175781, 98356161.90137763, "r"], "Support": [115, 59.2400016784668, 9027.449644740738, "s"], "Average Daily Volatility": 0, "Trend": 0, "Potential Profit": 0, "Average Low to Day Open": 0, "Average High to Day Open": 0, "Open Close Average": 0, "Price": 0.0, "Shares": 0, "Total Spent": 0}, {"Ticker": "CIH", "Rating": 71505184.07296753, "Resistance": [106, 1.1799999475479126, 69012056.15583941, "r"], "Support": [115, 0.8669999837875366, 2493127.91712811, "s"], "Average Daily Volatility": 0, "Trend": 0, "Potential Profit": 0, "Average Low to Day Open": 0, "Average High to Day Open": 0, "Open Close Average": 0, "Price": 0.0, "Shares": 0, "Total Spent": 0}, {"Ticker": "ALIM", "Rating": 49230279.29339403, "Resistance": [106, 6.2820000648498535, 9051516.69396441, "r"], "Support": [72, 4.01800012588501, 40178762.599429615, "s"], "Average Daily Volatility": 0, "Trend": 0, "Potential Profit": 0, "Average Low to Day Open": 0, "Average High to Day Open": 0, "Open Close Average": 0, "Price": 0.0, "Shares": 0, "Total Spent": 0}, {"Ticker": "NL", "Rating": 21261029.874660835, "Resistance": [94, 7.449999809265137, 20336692.08148651, "r"], "Support": [65, 5.481419579473239, 924337.7931743262, "s"], "Average Daily Volatility": 0, "Trend": 0, "Potential Profit": 0, "Average Low to Day Open": 0, "Average High to Day Open": 0, "Open Close Average": 0, "Price": 0.0, "Shares": 0, "Total Spent": 0}, {"Ticker": "HEP", "Rating": 3660430.3001190773, "Resistance": [111, 18.978037928565442, 3155291.3019825234, "r"], "Support": [85, 15.507879459077715, 505138.99813655403, "s"], "Average Daily Volatility": 0, "Trend": 0, "Potential Profit": 0, "Average Low to Day Open": 0, "Average High to Day Open": 0, "Open Close Average": 0, "Price": 0.0, "Shares": 0, "Total Spent": 0}, {"Ticker": "GNL", "Rating": 748124.7822409495, "Resistance": [111, 15.390000343322754, 13819.633120984096, "r"], "Support": [50, 13.171543590976993, 734305.1491199654, "s"], "Average Daily Volatility": 0, "Trend": 0, "Potential Profit": 0, "Average Low to Day Open": 0, "Average High to Day Open": 0, "Open Close Average": 0, "Price": 0.0, "Shares": 0, "Total Spent": 0}, {"Ticker": "CAPL", "Rating": 553784.1906011025, "Resistance": [117, 21.54245631287044, 542153.4994400694, "r"], "Support": [33, 17.952157903996945, 11630.69116103307, "s"], "Average Daily Volatility": 0, "Trend": 0, "Potential Profit": 0, "Average Low to Day Open": 0, "Average High to Day Open": 0, "Open Close Average": 0, "Price": 0.0, "Shares": 0, "Total Spent": 0}, {"Ticker": "CRNT", "Rating": 406865.38495655544, "Resistance": [96, 2.299999952316284, 343307.01227009785, "r"], "Support": [118, 1.7599999904632568, 63558.37268645756, "s"], "Average Daily Volatility": 0, "Trend": 0, "Potential Profit": 0, "Average Low to Day Open": 0, "Average High to Day Open": 0, "Open Close Average": 0, "Price": 0.0, "Shares": 0, "Total Spent": 0}, {"Ticker": "ALE", "Rating": 170665.390850699, "Resistance": [97, 68.45999908447266, 30068.589444505855, "r"], "Support": [118, 58.34000015258789, 140596.80140619315, "s"], "Average Daily Volatility": 0, "Trend": 0, "Potential Profit": 0, "Average Low to Day Open": 0, "Average High to Day Open": 0, "Open Close Average": 0, "Price": 0.0, "Shares": 0, "Total Spent": 0}, {"Ticker": "SHBI", "Rating": 161789.4359121387, "Resistance": [111, 21.209999084472656, 120500.8154737666, "r"], "Support": [104, 19.43000030517578, 41288.62043837208, "s"], "Average Daily Volatility": 0, "Trend": 0, "Potential Profit": 0, "Average Low to Day Open": 0, "Average High to Day Open": 0, "Open Close Average": 0, "Price": 0.0, "Shares": 0, "Total Spent": 0}, {"Ticker": "NHI", "Rating": 88088.13198633038, "Resistance": [98, 60.2400016784668, 57576.99910705721, "r"], "Support": [118, 50.220001220703125, 30511.13287927317, "s"], "Average Daily Volatility": 0, "Trend": 0, "Potential Profit": 0, "Average Low to Day Open": 0, "Average High to Day Open": 0, "Open Close Average": 0, "Price": 0.0, "Shares": 0, "Total Spent": 0}, {"Ticker": "CVR", "Rating": 46809.40090448628, "Resistance": [76, 27.67541001037703, 42105.16033469724, "r"], "Support": [118, 25.399999618530273, 4704.240569789042, "s"], "Average Daily Volatility": 0, "Trend": 0, "Potential Profit": 0, "Average Low to Day Open": 0, "Average High to Day Open": 0, "Open Close Average": 0, "Price": 0.0, "Shares": 0, "Total Spent": 0}, {"Ticker": "REIT", "Rating": 38660.95148645937, "Resistance": [110, 32.380001068115234, 37139.622944591094, "r"], "Support": [72, 26.442570205660633, 1521.328541868278, "s"], "Average Daily Volatility": 0, "Trend": 0, "Potential Profit": 0, "Average Low to Day Open": 0, "Average High to Day Open": 0, "Open Close Average": 0, "Price": 0.0, "Shares": 0, "Total Spent": 0}, {"Ticker": "EQL", "Rating": 33152.61625780634, "Resistance": [111, 110.30000305175781, 32102.398743315163, "r"], "Support": [72, 98.41313211806269, 1050.2175144911726, "s"], "Average Daily Volatility": 0, "Trend": 0, "Potential Profit": 0, "Average Low to Day Open": 0, "Average High to Day Open": 0, "Open Close Average": 0, "Price": 0.0, "Shares": 0, "Total Spent": 0}, {"Ticker": "USOI", "Rating": 9938.637167432187, "Resistance": [108, 5.612982551136451, 4119.512342424888, "r"], "Support": [85, 4.827089213698111, 5819.1248250072995, "s"], "Average Daily Volatility": 0, "Trend": 0, "Potential Profit": 0, "Average Low to Day Open": 0, "Average High to Day Open": 0, "Open Close Average": 0, "Price": 0.0, "Shares": 0, "Total Spent": 0}, {"Ticker": "TZPSU", "Rating": 128.30692755785842, "Resistance": [17, 10.149999618530273, 39.17236663263507, "r"], "Support": [25, 9.819999694824219, 89.13456092522334, "s"], "Average Daily Volatility": 0, "Trend": 0, "Potential Profit": 0, "Average Low to Day Open": 0, "Average High to Day Open": 0, "Open Close Average": 0, "Price": 0.0, "Shares": 0, "Total Spent": 0}, {"Ticker": "CPAR", "Rating": 57.939207536215676, "Resistance": [68, 9.779999732971191, 50.96101217416975, "r"], "Support": [72, 9.649999618530273, 6.978195362045921, "s"], "Average Daily Volatility": 0, "Trend": 0, "Potential Profit": 0, "Average Low to Day Open": 0, "Average High to Day Open": 0, "Open Close Average": 0, "Price": 0.0, "Shares": 0, "Total Spent": 0}, {"Ticker": "FTSM", "Rating": 18.243970325281055, "Resistance": [75, 59.667849389189335, 0.005996327405709863, "r"], "Support": [90, 59.39808824616817, 18.237973997875343, "s"], "Average Daily Volatility": 0, "Trend": 0, "Potential Profit": 0, "Average Low to Day Open": 0, "Average High to Day Open": 0, "Open Close Average": 0, "Price": 0.0, "Shares": 0, "Total Spent": 0}]